dirgen.py
dirgen-0.6.dist-info/DESCRIPTION.rst
dirgen-0.6.dist-info/METADATA
dirgen-0.6.dist-info/RECORD
dirgen-0.6.dist-info/WHEEL
dirgen-0.6.dist-info/entry_points.txt
dirgen-0.6.dist-info/metadata.json
dirgen-0.6.dist-info/top_level.txt
