Metadata-Version: 2.0
Name: dirgen
Version: 0.6
Summary: UNKNOWN
Home-page: UNKNOWN
Author: Jean-Paul Fiorini
Author-email: UNKNOWN
License: MIT
Platform: UNKNOWN
Requires-Dist: Click
